{"sections":{"main":{"type":"main-product","blocks":{"product_meta":{"type":"product_meta","settings":{"show_vendor":false,"show_tags":true,"show_sku":false,"show_product_rating":false,"show_taxes_included":false}},"2bca5785-2a5f-4ba5-b86b-73714c84c8cd":{"type":"shopify:\/\/apps\/judge-me-reviews\/blocks\/preview_badge\/61ccd3b1-a9f2-4160-9fe9-4fec8413e5d8","settings":{}},"0a1c1468-d8c2-410b-8d34-a97094f14eb4":{"type":"liquid","settings":{"liquid":"<div id=\"oneteam-like\"><\/div>"}},"description":{"type":"description","settings":{}},"quantity_selector":{"type":"quantity_selector","settings":{"show_label":false}},"variant_selector":{"type":"variant_selector","settings":{"selector_mode":"dropdown","show_color_swatch":false,"show_color_carousel":false,"size_chart":""}},"buy_buttons":{"type":"buy_buttons","settings":{"show_price_in_button":false,"show_payment_button":false}},"09f625ec-2f54-4c4a-b54a-4a1a841dd797":{"type":"store_pickup","disabled":true,"settings":{}},"e9496b3f-0dbd-4a1c-a173-068d98ede483":{"type":"share_buttons","settings":{}},"3fb1975c-df44-454d-8f29-4ed028dfe770":{"type":"liquid","disabled":true,"settings":{"liquid":"<p><a href=\"https:\/\/www.prexhobby.com\/#smile-points-activity-rules\"><strong>Earn P-REX Hobby Points <\/strong> <\/a><\/p>"}}},"block_order":["product_meta","2bca5785-2a5f-4ba5-b86b-73714c84c8cd","0a1c1468-d8c2-410b-8d34-a97094f14eb4","description","quantity_selector","variant_selector","buy_buttons","09f625ec-2f54-4c4a-b54a-4a1a841dd797","e9496b3f-0dbd-4a1c-a173-068d98ede483","3fb1975c-df44-454d-8f29-4ed028dfe770"],"settings":{"image_size":"large","stack_images":false,"show_thumbnails":true,"enable_image_zoom":true,"enable_video_looping":true,"product_status":true,"meta_text_color":"#ffffff","meta_text_bg":"#da5f6f"}},"judgeme_section_review_widget_c4a1":{"type":"apps","blocks":{"judgeme_review_widget_80db7ef7":{"type":"shopify:\/\/apps\/judge-me-reviews\/blocks\/review_widget\/61ccd3b1-a9f2-4160-9fe9-4fec8413e5d8","settings":{}}},"block_order":["judgeme_review_widget_80db7ef7"],"settings":{"include_margins":true}},"recently-viewed-products":{"type":"recently-viewed-products","disabled":true,"settings":{"title":"Recently viewed","show_product_info":true,"show_vendor":false,"show_color_swatch":false}},"c199a9e5-c0fa-499b-8e67-20bcdedb76ce":{"type":"custom-html","disabled":true,"settings":{"subheading":"","title":"","html":"<div id=\"disqus_thread\"><\/div>\n<script>\n    \/**\n    *  RECOMMENDED CONFIGURATION VARIABLES: EDIT AND UNCOMMENT THE SECTION BELOW TO INSERT DYNAMIC VALUES FROM YOUR PLATFORM OR CMS.\n    *  LEARN WHY DEFINING THESE VARIABLES IS IMPORTANT: https:\/\/disqus.com\/admin\/universalcode\/#configuration-variables    *\/\n    \/*\n    var disqus_config = function () {\n    this.page.url = PAGE_URL;  \/\/ Replace PAGE_URL with your page's canonical URL variable\n    this.page.identifier = PAGE_IDENTIFIER; \/\/ Replace PAGE_IDENTIFIER with your page's unique identifier variable\n    };\n    *\/\n    (function() { \/\/ DON'T EDIT BELOW THIS LINE\n    var d = document, s = d.createElement('script');\n    s.src = 'https:\/\/p-rex.disqus.com\/embed.js';\n    s.setAttribute('data-timestamp', +new Date());\n    (d.head || d.body).appendChild(s);\n    })();\n<\/script>\n<noscript>Please enable JavaScript to view the <a href=\"https:\/\/disqus.com\/?ref_noscript\">comments powered by Disqus.<\/a>\n<\/noscript>"}},"product-recommendations":{"type":"product-recommendations","settings":{"heading":"ANIME FANS WHO BOUGHT THIS ITEM ALSO BOUGHT","show_product_info":true,"show_vendor":false,"show_color_swatch":false}}},"order":["main","judgeme_section_review_widget_c4a1","recently-viewed-products","c199a9e5-c0fa-499b-8e67-20bcdedb76ce","product-recommendations"]}